arithmeticSubmodule/Operations.py
arithmeticSubmodule/__init__.py
arithmeticSubmodule-1.0.0.dist-info/METADATA
arithmeticSubmodule-1.0.0.dist-info/WHEEL
arithmeticSubmodule-1.0.0.dist-info/top_level.txt
arithmeticSubmodule-1.0.0.dist-info/RECORD
